pnm/audio.py
pnm/cli.py
pnm/config.py
pnm/diff.py
pnm/pnm.py
pnm/recorder.py
pnm/utils.py
pnm/artifacts/decoder_int8.onnx
pnm/artifacts/encoder_int8.onnx
pnm/artifacts/mel_filters_80.bin
pnm/artifacts/sample_practice.parquet
pnm-0.0.1.dist-info/METADATA
pnm-0.0.1.dist-info/WHEEL
pnm-0.0.1.dist-info/entry_points.txt
pnm-0.0.1.dist-info/top_level.txt
pnm-0.0.1.dist-info/RECORD
