Metadata-Version: 2.2
Name: pnm
Version: 0.0.1
Summary: Convert audio to phonetic text and practice improving your speech accent.
Home-page: https://github.com/pstwh/pnm
Keywords: phonetics,machine learning,neural network,english,speech,practice
Requires-Python: >=3.5, <4
Requires-Dist: pandas==2.2.3
Requires-Dist: scipy==1.13.1
Requires-Dist: pyaudio==0.2.14
Requires-Dist: pyarrow==18.1.0
Provides-Extra: cpu
Requires-Dist: onnxruntime==1.18.1; extra == "cpu"
Provides-Extra: gpu
Requires-Dist: onnxruntime-gpu==1.18.1; extra == "gpu"
Dynamic: description
Dynamic: description-content-type
Dynamic: home-page
Dynamic: keywords
Dynamic: provides-extra
Dynamic: requires-dist
Dynamic: requires-python
Dynamic: summary
